torch_dataset_mirror/__init__.py
torch_dataset_mirror-0.2.1.dist-info/LICENSE
torch_dataset_mirror-0.2.1.dist-info/METADATA
torch_dataset_mirror-0.2.1.dist-info/WHEEL
torch_dataset_mirror-0.2.1.dist-info/top_level.txt
torch_dataset_mirror-0.2.1.dist-info/RECORD
