Metadata-Version: 2.1
Name: torch-dataset-mirror
Version: 0.2.1
Summary: pytorch数据集国内镜像
Home-page: https://github.com/killf/pytorch_dataset_mirror
Author: killf
Author-email: killf@foxmail.com
License: Apache License
Platform: UNKNOWN
Classifier: Development Status :: 5 - Production/Stable
Classifier: Intended Audience :: Developers
Classifier: Programming Language :: Python :: 2
Classifier: Programming Language :: Python :: 3
Classifier: Operating System :: OS Independent
